shared/__init__.py
shared/__main__.py
shared/log.py
shared/schema/__init__.py
shared/schema/acl_entry.py
shared/schema/address.py
shared/schema/asset.py
shared/schema/attribute.py
shared/schema/bot.py
shared/schema/bots_node.py
shared/schema/collector.py
shared/schema/collectors_node.py
shared/schema/news_item.py
shared/schema/notification_template.py
shared/schema/organization.py
shared/schema/osint_source.py
shared/schema/parameter.py
shared/schema/parameter_value.py
shared/schema/presentation.py
shared/schema/presenter.py
shared/schema/presenters_node.py
shared/schema/product.py
shared/schema/product_type.py
shared/schema/publisher.py
shared/schema/publisher_preset.py
shared/schema/publishers_node.py
shared/schema/remote.py
shared/schema/report_item.py
shared/schema/report_item_type.py
shared/schema/role.py
shared/schema/tag_cloud.py
shared/schema/user.py
shared/schema/word_list.py
taranis_ng_shared-0.1.9.dist-info/METADATA
taranis_ng_shared-0.1.9.dist-info/WHEEL
taranis_ng_shared-0.1.9.dist-info/top_level.txt
taranis_ng_shared-0.1.9.dist-info/RECORD
