Metadata-Version: 2.1
Name: taranis-ng-shared
Version: 0.1.9
Summary: Taranis-NG Shared Classes
Home-page: https://github.com/SK-CERT/Taranis-NG
Author: SK-CERT, AIT
License: EUPL
Platform: any
Classifier: Programming Language :: Python
Classifier: Programming Language :: Python :: 3
Classifier: Programming Language :: Python :: 3.8
Classifier: Programming Language :: Python :: 3.9
Classifier: Programming Language :: Python :: 3.10
Classifier: Programming Language :: Python :: 3.11
Classifier: Topic :: Security
Requires-Python: >=3.8
Requires-Dist: marshmallow
Requires-Dist: marshmallow-enum
